LICENSE
MANIFEST.in
README.rst
pyproject.toml
setup.py
ModelSEEDpy_freiburgermsu.egg-info/PKG-INFO
ModelSEEDpy_freiburgermsu.egg-info/SOURCES.txt
ModelSEEDpy_freiburgermsu.egg-info/dependency_links.txt
ModelSEEDpy_freiburgermsu.egg-info/requires.txt
ModelSEEDpy_freiburgermsu.egg-info/top_level.txt
modelseedpy_freiburgermsu/__init__.py
modelseedpy_freiburgermsu/helpers.py
modelseedpy_freiburgermsu/biochem/__init__.py
modelseedpy_freiburgermsu/biochem/hierarchical_ontology.py
modelseedpy_freiburgermsu/biochem/modelseed_biochem.py
modelseedpy_freiburgermsu/biochem/modelseed_builder.py
modelseedpy_freiburgermsu/biochem/modelseed_compound.py
modelseedpy_freiburgermsu/biochem/modelseed_justification.py
modelseedpy_freiburgermsu/biochem/modelseed_reaction.py
modelseedpy_freiburgermsu/biochem/modelseed_to_cobra.py
modelseedpy_freiburgermsu/biochem/seed_object.py
modelseedpy_freiburgermsu/biochem/stoich_integration.py
modelseedpy_freiburgermsu/biochem/transporters.py
modelseedpy_freiburgermsu/biochem/utils.py
modelseedpy_freiburgermsu/community/__init__.py
modelseedpy_freiburgermsu/community/commhelper.py
modelseedpy_freiburgermsu/community/commphitting.py
modelseedpy_freiburgermsu/community/commscores_old.py
modelseedpy_freiburgermsu/community/datastandardization.py
modelseedpy_freiburgermsu/community/metquest_code.py
modelseedpy_freiburgermsu/community/mscommunity.py
modelseedpy_freiburgermsu/community/mskineticsfba.py
modelseedpy_freiburgermsu/community/mssteadycom.py
modelseedpy_freiburgermsu/core/__init__.py
modelseedpy_freiburgermsu/core/biolog.py
modelseedpy_freiburgermsu/core/exceptions.py
modelseedpy_freiburgermsu/core/fbahelper.py
modelseedpy_freiburgermsu/core/gapfillinghelper.py
modelseedpy_freiburgermsu/core/msatpcorrection.py
modelseedpy_freiburgermsu/core/msbuilder.py
modelseedpy_freiburgermsu/core/mseditorapi.py
modelseedpy_freiburgermsu/core/msgapfill.py
modelseedpy_freiburgermsu/core/msgenome.py
modelseedpy_freiburgermsu/core/msgenomeclassifier.py
modelseedpy_freiburgermsu/core/msgrowthphenotypes.py
modelseedpy_freiburgermsu/core/msmedia.py
modelseedpy_freiburgermsu/core/msminimalmedia.py
modelseedpy_freiburgermsu/core/msmodel.py
modelseedpy_freiburgermsu/core/msmodelutl.py
