Metadata-Version: 2.1
Name: ModelSEEDpy-freiburgermsu
Version: 0.3.1.5
Summary: Python package for building and analyzing models using ModelSEED
Home-page: https://github.com/ModelSEED/ModelSEEDpy
Author: Christopher Henry
Author-email: chenry@anl.gov
License: MIT License
Project-URL: Documentation, https://modelseedpy.readthedocs.io/en/latest/
Project-URL: Issues, https://github.com/ModelSEED/ModelSEEDpy/issues
Platform: UNKNOWN
Classifier: Development Status :: 3 - Alpha
Classifier: Topic :: Scientific/Engineering :: Bio-Informatics
Classifier: Intended Audience :: Science/Research
Classifier: Operating System :: OS Independent
Classifier: Programming Language :: Python :: 3.8
Classifier: Programming Language :: Python :: 3.9
Classifier: Programming Language :: Python :: 3.10
Classifier: Programming Language :: Python :: 3.11
Classifier: Natural Language :: English
License-File: LICENSE
